{
    "prefix": "!",
    "token": "",
    "messageSlowModeInterval": 3,
    "messageDeletionInterval": 3,
    "officers": {
        "idRole": ""
    },
    "categories": {
        "events": ""
    },
    "channels": {
        "roles": "",
        "config": "",
        "roster": "",
        "weapons": ""
    },
    "roles": {
        "tank": {
            "id": "",
            "idEmoji": ""
        },
        "heal": {
            "id": "",
            "idEmoji": ""
        },
        "dps": {
            "id": "",
            "idEmoji": ""
        }
    },
    "weapons": {
        "bow": "",
        "firestaff": "",
        "greataxe": "",
        "hatchet": "",
        "icegauntlet": "",
        "lifestaff": "",
        "musket": "",
        "rapier": "",
        "spear": "",
        "sword": "",
        "voidgauntlet": "",
        "warhammer": ""
    }
}